xtools/__init__.py
xtools/cache.py
xtools/config.py
xtools/find.py
xtools/matrix.py
xtools/unit.py
xtools/validator.py
xtools/storage/__init__.py
xtools/storage/s3/__init__.py
xtools/storage/s3/storage.py
xtools/utils/__init__.py
xtools/utils/color.py
xtools/utils/datetime.py
xtools/utils/encryption.py
xtools/utils/math.py
xtools/utils/text.py
xtools_py-0.2.1.dist-info/licenses/License
xtools_py-0.2.1.dist-info/METADATA
xtools_py-0.2.1.dist-info/WHEEL
xtools_py-0.2.1.dist-info/top_level.txt
xtools_py-0.2.1.dist-info/RECORD
