Metadata-Version: 2.4
Name: xtools-py
Version: 0.2.1
Summary: A set of useful utilities for Python developers
Home-page: https://github.com/SikWeet/xtools
Author: Xpeawey
Author-email: Xpeawey <girectx@example.com>
Classifier: Programming Language :: Python :: 3
Classifier: License :: OSI Approved :: MIT License
Classifier: Operating System :: OS Independent
Requires-Python: >=3.7
License-File: License
Requires-Dist: requests
Requires-Dist: cryptography
Dynamic: author
Dynamic: home-page
Dynamic: license-file
Dynamic: requires-python
